pylog/__init__.py
pythonlog-0.1.3.dist-info/LICENSE
pythonlog-0.1.3.dist-info/METADATA
pythonlog-0.1.3.dist-info/WHEEL
pythonlog-0.1.3.dist-info/top_level.txt
pythonlog-0.1.3.dist-info/RECORD
