Metadata-Version: 2.1
Name: pythonlog
Version: 0.1.3
Summary: The new python logger
Home-page: https://github.com/awesomelewis2007/pylog/
Author: Lewis Evans
Author-email: awesomelewis2007@gmail.com
License: GNU
Platform: UNKNOWN
License-File: LICENSE
